kangeo/__init__.py
kangeo/common.py
kangeo/kangeo.py
kangeo-0.0.2.dist-info/licenses/LICENSE
kangeo-0.0.2.dist-info/METADATA
kangeo-0.0.2.dist-info/WHEEL
kangeo-0.0.2.dist-info/entry_points.txt
kangeo-0.0.2.dist-info/top_level.txt
kangeo-0.0.2.dist-info/RECORD
