Metadata-Version: 2.4
Name: Kangeo
Version: 0.0.2
Summary: A geospatial python package
Author-email: Desmond Kangah <deskaygraphics@gmail.com>
License: MIT License
Project-URL: Homepage, https://github.com/deskaygraphics/Kangeo
Keywords: Kangeo
Classifier: Intended Audience :: Developers
Classifier: License :: OSI Approved :: MIT License
Classifier: Natural Language :: English
Classifier: Programming Language :: Python :: 3.8
Classifier: Programming Language :: Python :: 3.9
Classifier: Programming Language :: Python :: 3.10
Classifier: Programming Language :: Python :: 3.11
Classifier: Programming Language :: Python :: 3.12
Requires-Python: >=3.8
License-File: LICENSE
Requires-Dist: numpy
Provides-Extra: all
Requires-Dist: Kangeo[extra]; extra == "all"
Provides-Extra: extra
Requires-Dist: pandas; extra == "extra"
Dynamic: license-file
